{
  "Q742173": "gudebore",
  "Q7573059": "gudebore",
  "Q24946983": "gudebore",
  "Q17107651": "gudebore",
  "Q7285800": "gudebore",
  "Q6778637": "gudebore",
  "Q6434112": "gudebore",
  "Q5642869": "gudebore",
  "Q15840444": "gudebore",
  "Q65040984": "gudebore",
  "Q12971248": "gudebore",
  "Q47004974": "gudebore",
  "Q11076619": "gudebore",
  "Q2592256": "gudebore",
  "Q123441": "gudebore",
  "Q52406": "gudebore",
  "Q1051852": "gudebore",
  "Q4192299": "gudebore",
  "Q65044294": "gudebore",
  "Q496999": "gudebore",
  "Q12208569": "gudebore",
  "Q20726175": "gudebore",
  "Q7974369": "gudebore",
  "Q7808550": "gudebore",
  "Q997361": "gudebore",
  "Q7656154": "gudebore",
  "Q5016033": "gudebore",
  "Q3481800": "gudebore",
  "Q122963715": "gudebore",
  "Q13644362": "gudebore",
  "Q53698181": "gudebore",
  "Q1117173": "gudebore",
  "Q11826942": "gudebore",
  "Q4907305": "gudebore",
  "Q60761825": "gudebore",
  "Q5954806": "gudebore",
  "Q1753265": "gudebore",
  "Q11323173": "gudebore",
  "Q20034": "gudebore",
  "Q4917275": "gudebore",
  "Q4197759": "gudebore",
  "Q1684997": "gudebore",
  "Q3606603": "gudebore",
  "Q1811076": "gudebore",
  "Q2897203": "gudebore",
  "Q61078926": "gudebore",
  "Q2902532": "segngjeten",
  "Q120176394": "segngjeten",
  "Q2891036": "segngjeten",
  "Q747457": "segngjeten",
  "Q1506811": "segngjeten",
  "Q5286620": "segngjeten",
  "Q271555": "segngjeten",
  "Q2428787": "segngjeten",
  "Q16935381": "segngjeten",
  "Q19646375": "segngjeten",
  "Q2827721": "segngjeten",
  "Q6863335": "segngjeten",
  "Q60740502": "segngjeten",
  "Q1057256": "segngjeten",
  "Q3257494": "segngjeten",
  "Q19573431": "segngjeten",
  "Q107292775": "segngjeten",
  "Q16738075": "segngjeten",
  "Q2096886": "segngjeten",
  "Q5254542": "segngjeten",
  "Q3198369": "segngjeten",
  "Q1473422": "segngjeten",
  "Q12489250": "segngjeten",
  "Q4201329": "segngjeten",
  "Q5004810": "segngjeten",
  "Q12593636": "segngjeten",
  "Q3505757": "segngjeten",
  "Q17485383": "segngjeten",
  "Q10316276": "segngjeten",
  "Q85762176": "segngjeten",
  "Q113114616": "segngjeten",
  "Q995376": "segngjeten",
  "Q47005562": "segngjeten",
  "Q1228260": "segngjeten",
  "Q19727704": "segngjeten",
  "Q28402897": "segngjeten",
  "Q980840": "segngjeten",
  "Q1435874": "segngjeten",
  "Q26806341": "segngjeten",
  "Q3087626": "segngjeten",
  "Q4823701": "segngjeten",
  "Q7142949": "segngjeten",
  "Q97178289": "segngjeten",
  "Q83143290": "segngjeten",
  "Q30186": "segngjeten",
  "Q78210944": "segngjeten",
  "Q3280441": "segngjeten",
  "Q16931986": "segngjeten",
  "Q1293258": "segngjeten",
  "Q28163754": "segngjeten",
  "Q3594122": "segngjeten",
  "Q1414887": "segngjeten",
  "Q5574228": "segngjeten",
  "Q69214": "segngjeten",
  "Q2216156": "segngjeten",
  "Q3234514": "segngjeten",
  "Q2142880": "segngjeten",
  "Q432308": "segngjeten",
  "Q1268122": "segngjeten",
  "Q113002647": "segngjeten",
  "Q865325": "segngjeten",
  "Q122999857": "segngjeten",
  "Q5004813": "segngjeten",
  "Q4264051": "segngjeten",
  "Q13231338": "segngjeten",
  "Q138024294": "segngjeten",
  "Q107489664": "segngjeten",
  "Q10698992": "segngjeten",
  "Q531184": "segngjeten",
  "Q65066634": "segngjeten",
  "Q6027777": "segngjeten",
  "Q16850213": "segngjeten",
  "Q19746250": "segngjeten",
  "Q7228884": "segngjeten",
  "Q152981": "segngjeten",
  "Q7080021": "segngjeten",
  "Q867426": "segngjeten",
  "Q136842110": "segngjeten",
  "Q16963428": "segngjeten",
  "Q4390491": "segngjeten",
  "Q281278": "segngjeten",
  "Q7650627": "segngjeten",
  "Q4206002": "segngjeten",
  "Q878318": "segngjeten",
  "Q934095": "segngjeten",
  "Q1683716": "segngjeten",
  "Q107610602": "segngjeten",
  "Q1061604": "segngjeten",
  "Q65072654": "segngjeten",
  "Q170883": "segngjeten",
  "Q683495": "segngjeten",
  "Q1505500": "sjeldgjevt",
  "Q2056399": "sjeldgjevt",
  "Q4202016": "sjeldgjevt",
  "Q11078597": "sjeldgjevt",
  "Q1855212": "sjeldgjevt",
  "Q1068574": "sjeldgjevt",
  "Q8066663": "sjeldgjevt",
  "Q1756289": "sjeldgjevt",
  "Q131737431": "sjeldgjevt",
  "Q30737843": "sjeldgjevt",
  "Q115802987": "sjeldgjevt",
  "Q6088454": "sjeldgjevt",
  "Q3497556": "sjeldgjevt",
  "Q27909648": "sjeldgjevt",
  "Q3909175": "sjeldgjevt",
  "Q702692": "sjeldgjevt",
  "Q6502741": "sjeldgjevt",
  "Q97101726": "sjeldgjevt",
  "Q213105": "sjeldgjevt",
  "Q5832771": "sjeldgjevt",
  "Q122723474": "sjeldgjevt",
  "Q125372014": "sjeldgjevt",
  "Q1432724": "sjeldgjevt",
  "Q10391691": "sjeldgjevt",
  "Q2364865": "sjeldgjevt",
  "Q19728050": "sjeldgjevt",
  "Q7171328": "sjeldgjevt",
  "Q96402831": "sjeldgjevt",
  "Q3104777": "sjeldgjevt",
  "Q1076874": "sjeldgjevt",
  "Q104844158": "sjeldgjevt",
  "Q13096825": "sjeldgjevt",
  "Q1137574": "sjeldgjevt",
  "Q15895670": "sjeldgjevt",
  "Q18943775": "sjeldgjevt",
  "Q4208144": "sjeldgjevt",
  "Q2023763": "sjeldgjevt",
  "Q7489821": "sjeldgjevt",
  "Q3075310": "sjeldgjevt",
  "Q3026484": "sjeldgjevt",
  "Q16773515": "sjeldgjevt",
  "Q12758929": "sjeldgjevt",
  "Q5565095": "sjeldgjevt",
  "Q192892": "sjeldgjevt",
  "Q12473662": "sjeldgjevt",
  "Q828043": "sjeldgjevt",
  "Q107358883": "sjeldgjevt",
  "Q14916156": "sjeldgjevt",
  "Q929487": "sjeldgjevt",
  "Q4818958": "sjeldgjevt",
  "Q681770": "sjeldgjevt",
  "Q4197962": "sjeldgjevt",
  "Q123124821": "sjeldgjevt",
  "Q1988970": "sjeldgjevt",
  "Q7139220": "sjeldgjevt",
  "Q10936666": "sjeldgjevt",
  "Q5389704": "sjeldgjevt",
  "Q4833788": "sjeldgjevt",
  "Q135921153": "sjeldgjevt",
  "Q17164196": "sjeldgjevt",
  "Q17101058": "sjeldgjevt",
  "Q12512536": "sjeldgjevt",
  "Q60761452": "sjeldgjevt",
  "Q3420368": "sjeldgjevt",
  "Q6967048": "sjeldgjevt",
  "Q600438": "sjeldgjevt",
  "Q923729": "sjeldgjevt",
  "Q182339": "sjeldgjevt",
  "Q613717": "sjeldgjevt",
  "Q16913644": "sjeldgjevt",
  "Q104858644": "sjeldgjevt",
  "Q1760470": "sjeldgjevt",
  "Q17005230": "sjeldgjevt",
  "Q17104228": "sjeldgjevt",
  "Q56292893": "sjeldgjevt",
  "Q1815839": "sjeldgjevt",
  "Q7548366": "sjeldgjevt",
  "Q1141370": "sjeldgjevt",
  "Q83603766": "sjeldgjevt",
  "Q20065": "sjeldgjevt",
  "Q60754611": "sjeldgjevt",
  "Q1083840": "sjeldgjevt",
  "Q63228690": "sjeldgjevt",
  "Q107007191": "sjeldgjevt",
  "Q25056844": "sjeldgjevt",
  "Q3080164": "sjeldgjevt",
  "Q316849": "sjeldgjevt",
  "Q1452513": "sjeldgjevt",
  "Q17019149": "sjeldgjevt",
  "Q924689": "sjeldgjevt",
  "Q1138371": "sjeldgjevt",
  "Q707788": "sjeldgjevt",
  "Q60748979": "sjeldgjevt",
  "Q16706914": "sjeldgjevt",
  "Q7197643": "sjeldgjevt",
  "Q5202996": "sjeldgjevt",
  "Q30599785": "sjeldgjevt",
  "Q65117391": "sjeldgjevt",
  "Q9696648": "sjeldgjevt",
  "Q1141574": "sjeldgjevt",
  "Q2723965": "sjeldgjevt",
  "Q3327283": "sjeldgjevt",
  "Q19711295": "sjeldgjevt",
  "Q3274058": "sjeldgjevt",
  "Q70241": "sjeldgjevt",
  "Q12203234": "sjeldgjevt",
  "Q7908657": "sjeldgjevt",
  "Q20060232": "sjeldgjevt",
  "Q3382504": "sjeldgjevt",
  "Q7799573": "sjeldgjevt",
  "Q91908928": "sjeldgjevt",
  "Q2180951": "sjeldgjevt",
  "Q7272094": "sjeldgjevt",
  "Q4920553": "sjeldgjevt",
  "Q19724350": "sjeldgjevt",
  "Q597921": "sjeldgjevt",
  "Q1131837": "sjeldgjevt",
  "Q7811421": "sjeldgjevt",
  "Q777487": "sjeldgjevt",
  "Q48880901": "sjeldgjevt",
  "Q107486466": "sjeldgjevt",
  "Q1349413": "sjeldgjevt",
  "Q5120165": "sjeldgjevt",
  "Q126961970": "sjeldgjevt",
  "Q1286804": "sjeldgjevt",
  "Q12508588": "sjeldgjevt",
  "Q4835804": "sjeldgjevt",
  "Q17109441": "sjeldgjevt",
  "Q356346": "sjeldgjevt",
  "Q9026659": "sjeldgjevt",
  "Q19723512": "sjeldgjevt",
  "Q8077757": "sjeldgjevt",
  "Q12553023": "sjeldgjevt",
  "Q2580257": "sjeldgjevt",
  "Q16911615": "sjeldgjevt",
  "Q5305996": "sjeldgjevt",
  "Q7124456": "sjeldgjevt",
  "Q6944521": "sjeldgjevt",
  "Q1420442": "sjeldgjevt",
  "Q55150793": "sjeldgjevt",
  "Q21781581": "sjeldgjevt",
  "Q1397169": "sjeldgjevt",
  "Q950976": "sjeldgjevt",
  "Q5202956": "sjeldgjevt",
  "Q15730394": "sjeldgjevt",
  "Q2746599": "sjeldgjevt",
  "Q113038928": "sjeldgjevt",
  "Q130097": "sjeldgjevt",
  "Q574483": "sjeldgjevt",
  "Q6387099": "sjeldgjevt",
  "Q627744": "sjeldgjevt",
  "Q872625": "sjeldgjevt",
  "Q5503409": "sjeldgjevt",
  "Q111381747": "sjeldgjevt",
  "Q85767584": "sjeldgjevt",
  "Q18357204": "sjeldgjevt",
  "Q610130": "sjeldgjevt",
  "Q16241452": "sjeldgjevt",
  "Q154043": "sjeldgjevt",
  "Q3082973": "sjeldgjevt",
  "Q2255787": "sjeldgjevt",
  "Q5373825": "sjeldgjevt",
  "Q3697035": "sjeldgjevt",
  "Q57981532": "sjeldgjevt",
  "Q133504015": "sjeldgjevt",
  "Q3085085": "sjeldgjevt",
  "Q1464898": "sjeldgjevt",
  "Q17050490": "sjeldgjevt",
  "Q2548949": "sjeldgjevt",
  "Q6827067": "sjeldgjevt",
  "Q187495": "sjeldgjevt",
  "Q1227144": "sjeldgjevt",
  "Q3537474": "sjeldgjevt",
  "Q3594113": "sjeldgjevt",
  "Q5057827": "sjeldgjevt",
  "Q876096": "sjeldgjevt",
  "Q2654880": "sjeldgjevt",
  "Q5523464": "sjeldgjevt",
  "Q16182271": "sjeldgjevt",
  "Q389574": "sjeldgjevt",
  "Q2955932": "sjeldgjevt",
  "Q7855577": "sjeldgjevt",
  "Q12492825": "sjeldgjevt",
  "Q17054040": "sjeldgjevt",
  "Q16411925": "sjeldgjevt",
  "Q862557": "sjeldgjevt",
  "Q96386264": "sjeldgjevt",
  "Q3380255": "sjeldgjevt",
  "Q56307726": "sjeldgjevt",
  "Q7200291": "sjeldgjevt",
  "Q1133127": "sjeldgjevt",
  "Q5055611": "sjeldgjevt",
  "Q847652": "sjeldgjevt",
  "Q598222": "sjeldgjevt",
  "Q5257857": "sjeldgjevt",
  "Q12200": "sjeldgjevt",
  "Q6663": "sjeldgjevt",
  "Q12849581": "sjeldgjevt",
  "Q905527": "sjeldgjevt",
  "Q12491347": "sjeldgjevt",
  "Q108366890": "sjeldgjevt",
  "Q3462362": "sjeldgjevt",
  "Q4796545": "sjeldgjevt",
  "Q139500157": "sjeldgjevt",
  "Q4205452": "sjeldgjevt",
  "Q1095315": "sjeldgjevt",
  "Q15935161": "sjeldgjevt",
  "Q106194785": "sjeldgjevt",
  "Q4748563": "sjeldgjevt",
  "Q2393807": "sjeldgjevt",
  "Q5084201": "sjeldgjevt",
  "Q16975890": "sjeldgjevt",
  "Q4373369": "sjeldgjevt",
  "Q4293923": "sjeldgjevt",
  "Q129900296": "sjeldgjevt",
  "Q6981917": "sjeldgjevt",
  "Q30682135": "sjeldgjevt",
  "Q10752179": "sjeldgjevt",
  "Q1397036": "sjeldgjevt",
  "Q2721752": "sjeldgjevt",
  "Q3896505": "sjeldgjevt",
  "Q85744456": "sjeldgjevt",
  "Q489703": "sjeldgjevt",
  "Q3273951": "sjeldgjevt",
  "Q2998597": "sjeldgjevt",
  "Q1275331": "sjeldgjevt",
  "Q1200514": "sjeldgjevt",
  "Q5331853": "sjeldgjevt",
  "Q28208795": "sjeldgjevt",
  "Q7796150": "vanleg",
  "Q1236601": "vanleg",
  "Q130465645": "vanleg",
  "Q4887922": "vanleg",
  "Q85814488": "vanleg",
  "Q2395693": "vanleg",
  "Q2899201": "vanleg",
  "Q60762918": "vanleg",
  "Q152834": "vanleg",
  "Q2468860": "vanleg",
  "Q19573003": "vanleg",
  "Q7370537": "vanleg",
  "Q10499831": "vanleg",
  "Q542790": "vanleg",
  "Q12097130": "vanleg",
  "Q2681008": "vanleg",
  "Q262796": "vanleg",
  "Q133270012": "vanleg",
  "Q643225": "vanleg",
  "Q7309432": "vanleg",
  "Q4103061": "vanleg",
  "Q1067884": "vanleg",
  "Q7124365": "vanleg",
  "Q2255703": "vanleg",
  "Q17590922": "vanleg",
  "Q12500155": "vanleg",
  "Q124613458": "vanleg",
  "Q1827035": "vanleg",
  "Q62271704": "vanleg",
  "Q5366437": "vanleg",
  "Q879133": "vanleg",
  "Q19851743": "vanleg",
  "Q16307825": "vanleg",
  "Q5684686": "vanleg",
  "Q124053312": "vanleg",
  "Q20016": "vanleg",
  "Q1135831": "vanleg",
  "Q2961907": "vanleg",
  "Q14914664": "vanleg",
  "Q14943090": "vanleg",
  "Q4199436": "vanleg",
  "Q16836245": "vanleg",
  "Q5171054": "vanleg",
  "Q3629971": "vanleg",
  "Q705123": "vanleg",
  "Q107308168": "vanleg",
  "Q136486705": "vanleg",
  "Q110101486": "vanleg",
  "Q4272221": "vanleg",
  "Q1967823": "vanleg",
  "Q2725826": "vanleg",
  "Q966824": "vanleg",
  "Q1561248": "vanleg",
  "Q720230": "vanleg",
  "Q135921156": "vanleg",
  "Q702104": "vanleg",
  "Q2060858": "vanleg",
  "Q1195276": "vanleg",
  "Q2625025": "vanleg",
  "Q5862467": "vanleg",
  "Q96374874": "vanleg",
  "Q11114189": "vanleg",
  "Q86665833": "vanleg",
  "Q16951552": "vanleg",
  "Q4413207": "vanleg",
  "Q55629806": "vanleg",
  "Q1147853": "vanleg",
  "Q1004735": "vanleg",
  "Q34715": "vanleg",
  "Q12812242": "vanleg",
  "Q119541430": "vanleg",
  "Q116745181": "vanleg",
  "Q107358612": "vanleg",
  "Q3893200": "vanleg",
  "Q7525342": "vanleg",
  "Q12808559": "vanleg",
  "Q3897489": "vanleg",
  "Q2974872": "vanleg",
  "Q131319334": "vanleg",
  "Q205762": "vanleg",
  "Q26884006": "vanleg",
  "Q2457455": "vanleg",
  "Q16937065": "vanleg",
  "Q53844640": "vanleg",
  "Q6107288": "vanleg",
  "Q860170": "vanleg",
  "Q28163759": "vanleg",
  "Q18111413": "vanleg",
  "Q64216206": "vanleg",
  "Q1372313": "vanleg",
  "Q12500151": "vanleg",
  "Q1364509": "vanleg",
  "Q1420371": "vanleg",
  "Q17750349": "vanleg",
  "Q5331480": "vanleg",
  "Q59260812": "vanleg",
  "Q7136846": "vanleg",
  "Q111046463": "vanleg",
  "Q17083249": "vanleg",
  "Q685680": "vanleg",
  "Q6585018": "vanleg",
  "Q6789614": "vanleg",
  "Q10659978": "vanleg",
  "Q6404116": "vanleg",
  "Q2485491": "vanleg",
  "Q997633": "vanleg",
  "Q3043512": "vanleg",
  "Q96371762": "vanleg",
  "Q1284887": "vanleg",
  "Q12709581": "vanleg",
  "Q941004": "vanleg",
  "Q107323701": "vanleg",
  "Q1537922": "vanleg",
  "Q10271107": "vanleg",
  "Q19747511": "vanleg",
  "Q3441149": "vanleg",
  "Q138545531": "vanleg",
  "Q15427731": "vanleg",
  "Q107357106": "vanleg",
  "Q2635144": "vanleg",
  "Q107358554": "vanleg",
  "Q6393299": "vanleg",
  "Q107416756": "vanleg",
  "Q21087825": "vanleg",
  "Q10978475": "vanleg",
  "Q18356332": "vanleg",
  "Q491517": "vanleg",
  "Q6421494": "vanleg",
  "Q209486": "vanleg",
  "Q48774226": "vanleg",
  "Q6009729": "vanleg",
  "Q5503628": "vanleg",
  "Q367225": "vanleg",
  "Q5971200": "vanleg",
  "Q1197104": "vanleg",
  "Q123310300": "vanleg",
  "Q5208692": "vanleg",
  "Q872611": "vanleg",
  "Q55632427": "vanleg",
  "Q7648934": "vanleg",
  "Q21424783": "vanleg",
  "Q112669702": "vanleg",
  "Q30326666": "vanleg",
  "Q3373858": "vanleg",
  "Q1069097": "vanleg",
  "Q113002820": "vanleg",
  "Q18948079": "vanleg",
  "Q60761467": "vanleg",
  "Q7370536": "vanleg",
  "Q12491": "vanleg",
  "Q860465": "vanleg",
  "Q564271": "vanleg",
  "Q1202255": "vanleg",
  "Q20826672": "vanleg",
  "Q12070251": "vanleg",
  "Q4164571": "vanleg",
  "Q7461448": "vanleg",
  "Q7231310": "vanleg",
  "Q25043234": "vanleg",
  "Q481774": "vanleg",
  "Q3393853": "vanleg",
  "Q96385320": "vanleg",
  "Q188788": "vanleg",
  "Q2339814": "vanleg",
  "Q3847532": "vanleg",
  "Q2916235": "vanleg",
  "Q703286": "vanleg",
  "Q138479165": "vanleg",
  "Q1190475": "vanleg",
  "Q25043246": "vanleg",
  "Q120069075": "vanleg",
  "Q17122679": "vanleg",
  "Q4272202": "vanleg",
  "Q203886": "vanleg",
  "Q12518675": "vanleg",
  "Q15794115": "vanleg",
  "Q586307": "vanleg",
  "Q104792798": "vanleg",
  "Q5528400": "vanleg",
  "Q96742825": "vanleg",
  "Q25038426": "vanleg",
  "Q3686985": "vanleg",
  "Q6395436": "vanleg",
  "Q3236175": "vanleg",
  "Q3848253": "vanleg",
  "Q1094305": "vanleg",
  "Q19725078": "vanleg",
  "Q11142810": "vanleg",
  "Q1703796": "vanleg",
  "Q47005642": "vanleg",
  "Q7695520": "vanleg",
  "Q5103662": "vanleg",
  "Q12484057": "vanleg",
  "Q612661": "vanleg",
  "Q19944109": "vanleg",
  "Q85764627": "vanleg",
  "Q12496028": "vanleg",
  "Q138011108": "vanleg",
  "Q6570706": "vanleg",
  "Q951525": "vanleg",
  "Q19838749": "vanleg",
  "Q3234931": "vanleg",
  "Q25066353": "vanleg",
  "Q2553843": "vanleg",
  "Q3950519": "vanleg",
  "Q1639853": "vanleg",
  "Q4803469": "vanleg",
  "Q1275518": "vanleg",
  "Q2634430": "vanleg",
  "Q2478703": "vanleg",
  "Q2445410": "vanleg",
  "Q55593280": "vanleg",
  "Q2919135": "vanleg",
  "Q3382650": "vanleg",
  "Q7852883": "vanleg",
  "Q500724": "vanleg",
  "Q19749023": "vanleg",
  "Q25055799": "vanleg",
  "Q7572829": "vanleg",
  "Q3051726": "vanleg",
  "Q5262528": "vanleg",
  "Q7554467": "vanleg",
  "Q3420363": "vanleg",
  "Q11113287": "vanleg",
  "Q115766697": "vanleg",
  "Q7127953": "vanleg",
  "Q868158": "vanleg",
  "Q5202957": "vanleg",
  "Q5182787": "vanleg",
  "Q7476075": "vanleg",
  "Q3477693": "vanleg",
  "Q12841103": "vanleg",
  "Q1052236": "vanleg",
  "Q5615325": "vanleg",
  "Q3823969": "vanleg",
  "Q11996678": "vanleg",
  "Q7193747": "vanleg",
  "Q3232406": "vanleg",
  "Q19738844": "vanleg",
  "Q1886687": "vanleg",
  "Q1139527": "vanleg",
  "Q11343150": "vanleg",
  "Q112911886": "vanleg",
  "Q7565043": "vanleg",
  "Q430583": "vanleg",
  "Q284983": "vanleg",
  "Q578473": "vanleg",
  "Q137921543": "vanleg",
  "Q4997935": "vanleg",
  "Q17006531": "vanleg",
  "Q3097864": "vanleg",
  "Q1048130": "vanleg",
  "Q3244647": "vanleg",
  "Q3327301": "vanleg",
  "Q11162": "vanleg",
  "Q2274269": "vanleg",
  "Q390823": "vanleg",
  "Q85760630": "vanleg",
  "Q106977722": "vanleg",
  "Q5004800": "vanleg",
  "Q50634": "vanleg",
  "Q1555816": "vanleg",
  "Q12233354": "vanleg",
  "Q17998502": "vanleg",
  "Q1059273": "vanleg",
  "Q1726195": "vanleg",
  "Q5261363": "vanleg",
  "Q1244010": "vanleg",
  "Q20427541": "vanleg",
  "Q12106077": "vanleg",
  "Q4822464": "vanleg",
  "Q1479399": "vanleg",
  "Q209304": "vanleg",
  "Q11957646": "vanleg",
  "Q120682642": "vanleg",
  "Q107357284": "vanleg",
  "Q141293": "vanleg",
  "Q85801047": "vanleg",
  "Q7706778": "vanleg",
  "Q2879351": "vanleg",
  "Q30587986": "vanleg",
  "Q200527": "vanleg",
  "Q10725547": "vanleg",
  "Q2495505": "vanleg",
  "Q3678059": "vanleg",
  "Q10567133": "vanleg",
  "Q7208574": "vanleg",
  "Q4739207": "vanleg",
  "Q3044741": "vanleg",
  "Q655235": "vanleg",
  "Q85800897": "vanleg",
  "Q6904753": "vanleg",
  "Q1093380": "vanleg",
  "Q16847884": "vanleg",
  "Q4205456": "vanleg",
  "Q5360549": "vanleg",
  "Q118574754": "vanleg",
  "Q13013315": "vanleg",
  "Q22348764": "vanleg",
  "Q713869": "vanleg",
  "Q5004794": "vanleg",
  "Q6027429": "vanleg",
  "Q12964893": "vanleg",
  "Q65589417": "vanleg",
  "Q1352897": "vanleg",
  "Q12555954": "vanleg",
  "Q888832": "vanleg",
  "Q1934690": "vanleg",
  "Q60150397": "vanleg",
  "Q3881787": "vanleg",
  "Q108887239": "vanleg",
  "Q1721014": "vanleg",
  "Q4876265": "vanleg",
  "Q980388": "vanleg",
  "Q15976317": "vanleg",
  "Q2082064": "vanleg",
  "Q24027629": "vanleg",
  "Q6429813": "vanleg",
  "Q10669467": "vanleg",
  "Q10971166": "vanleg",
  "Q16966417": "vanleg",
  "Q703147": "vanleg",
  "Q15656515": "vanleg",
  "Q19732533": "vanleg",
  "Q623247": "vanleg",
  "Q7504007": "vanleg",
  "Q264558": "vanleg",
  "Q106653772": "vanleg",
  "Q5123542": "vanleg",
  "Q31173508": "vanleg",
  "Q5262436": "vanleg",
  "Q30324437": "vanleg",
  "Q12287205": "vanleg",
  "Q2527136": "vanleg",
  "Q171983": "vanleg",
  "Q16942586": "vanleg",
  "Q453174": "vanleg",
  "Q16498169": "vanleg",
  "Q572275": "vanleg",
  "Q127433632": "vanleg",
  "Q10931125": "vanleg",
  "Q6379127": "vanleg",
  "Q17000111": "vanleg",
  "Q1328767": "vanleg",
  "Q124434638": "vanleg",
  "Q5015278": "vanleg",
  "Q16888187": "vanleg",
  "Q109045517": "vanleg",
  "Q5180222": "vanleg",
  "Q124317521": "vanleg",
  "Q25220535": "vanleg",
  "Q848957": "vanleg",
  "Q29887669": "vanleg",
  "Q715040": "vanleg",
  "Q7087232": "vanleg",
  "Q605444": "vanleg",
  "Q648352": "vanleg",
  "Q1520293": "vanleg",
  "Q4208661": "vanleg",
  "Q16773140": "vanleg",
  "Q4189322": "vanleg",
  "Q1853883": "vanleg",
  "Q7809258": "vanleg",
  "Q10394334": "vanleg",
  "Q4203530": "vanleg",
  "Q1146771": "vanleg",
  "Q5684811": "vanleg",
  "Q31173018": "vanleg",
  "Q7000528": "vanleg",
  "Q1145039": "vanleg",
  "Q11853198": "vanleg",
  "Q5047987": "vanleg",
  "Q952366": "vanleg",
  "Q3243732": "vanleg",
  "Q6374193": "vanleg",
  "Q863794": "vanleg",
  "Q861293": "vanleg",
  "Q18542598": "vanleg",
  "Q13434162": "vanleg",
  "Q12492558": "vanleg",
  "Q24906665": "vanleg",
  "Q137270645": "vanleg",
  "Q2317875": "vanleg",
  "Q495360": "vanleg",
  "Q2402333": "vanleg",
  "Q28163731": "vanleg",
  "Q6528443": "vanleg",
  "Q19727660": "vanleg",
  "Q12492887": "vanleg",
  "Q15801159": "vanleg",
  "Q876624": "vanleg",
  "Q60760520": "vanleg",
  "Q21014439": "vanleg",
  "Q3391647": "vanleg",
  "Q121115158": "vanleg",
  "Q4189615": "vanleg",
  "Q12033864": "vanleg",
  "Q824592": "vanleg",
  "Q64358326": "vanleg",
  "Q63527491": "vanleg",
  "Q1539635": "vanleg",
  "Q1761000": "vanleg",
  "Q19738539": "vanleg",
  "Q1572563": "vanleg",
  "Q25052639": "vanleg",
  "Q17997301": "vanleg",
  "Q827654": "vanleg",
  "Q1367718": "vanleg",
  "Q11269155": "vanleg",
  "Q3083513": "vanleg",
  "Q1142841": "vanleg",
  "Q2905237": "vanleg",
  "Q5560177": "vanleg",
  "Q16573500": "vanleg",
  "Q104864044": "vanleg",
  "Q473271": "vanleg",
  "Q3272930": "vanleg",
  "Q6754314": "vanleg",
  "Q136922": "vanleg",
  "Q97360429": "vanleg",
  "Q85735249": "vanleg",
  "Q5162437": "vanleg",
  "Q18883046": "vanleg",
  "Q534420": "vanleg",
  "Q6967046": "vanleg",
  "Q564567": "vanleg",
  "Q6080770": "vanleg",
  "Q12522818": "vanleg",
  "Q7143016": "vanleg",
  "Q6967043": "vanleg",
  "Q111705550": "vanleg",
  "Q28219522": "vanleg",
  "Q12711188": "vanleg",
  "Q60760541": "vanleg",
  "Q6581424": "vanleg",
  "Q29019793": "vanleg",
  "Q5092519": "vanleg",
  "Q131852182": "vanleg",
  "Q2414031": "vanleg",
  "Q6192335": "vanleg",
  "Q18043321": "vanleg",
  "Q123015196": "vanleg",
  "Q2632589": "vanleg",
  "Q7377183": "vanleg",
  "Q7666782": "vanleg",
  "Q25041417": "vanleg",
  "Q1920415": "vanleg",
  "Q1105512": "vanleg",
  "Q575790": "vanleg",
  "Q120395550": "vanleg",
  "Q31740176": "vanleg",
  "Q957776": "vanleg",
  "Q3503333": "vanleg",
  "Q3535543": "vanleg",
  "Q61366482": "vanleg",
  "Q12219244": "vanleg",
  "Q2967557": "vanleg",
  "Q642702": "vanleg",
  "Q6066244": "vanleg",
  "Q2482979": "vanleg",
  "Q20987994": "vanleg",
  "Q4811799": "vanleg",
  "Q590076": "vanleg",
  "Q130553333": "vanleg",
  "Q893318": "vanleg",
  "Q32360952": "vanleg",
  "Q6729605": "vanleg",
  "Q907849": "vanleg",
  "Q2548021": "vanleg",
  "Q22929120": "vanleg",
  "Q1868851": "vanleg",
  "Q7446149": "vanleg",
  "Q87840119": "vanleg",
  "Q375": "vanleg",
  "Q6493": "vanleg",
  "Q35586024": "vanleg",
  "Q97654410": "vanleg",
  "Q1152783": "vanleg",
  "Q1476953": "vanleg",
  "Q109436498": "vanleg",
  "Q839910": "vanleg",
  "Q20984265": "vanleg",
  "Q913411": "vanleg",
  "Q56308209": "vanleg",
  "Q2915859": "vanleg",
  "Q3948384": "vanleg",
  "Q2835652": "vanleg",
  "Q10964995": "vanleg",
  "Q107357988": "vanleg",
  "Q44541": "vanleg",
  "Q5571808": "vanleg",
  "Q14918748": "vanleg",
  "Q4899060": "vanleg",
  "Q703313": "vanleg",
  "Q1218450": "vanleg",
  "Q1243795": "vanleg",
  "Q15042119": "vanleg",
  "Q12492826": "vanleg",
  "Q12476406": "vanleg",
  "Q81615502": "vanleg",
  "Q3301336": "vanleg",
  "Q6967051": "vanleg",
  "Q5864774": "vanleg",
  "Q1757401": "vanleg",
  "Q2101181": "vanleg",
  "Q2425845": "vanleg",
  "Q1626853": "vanleg",
  "Q5702275": "vanleg",
  "Q4200659": "vanleg",
  "Q2565922": "vanleg",
  "Q1026488": "vanleg",
  "Q11682627": "vanleg",
  "Q1559248": "vanleg",
  "Q1136876": "vanleg",
  "Q7307455": "vanleg",
  "Q865004": "vanleg",
  "Q5522421": "vanleg",
  "Q1501043": "vanleg",
  "Q464545": "vanleg",
  "Q305329": "vanleg",
  "Q17035821": "vanleg",
  "Q7178377": "vanleg",
  "Q22328037": "vanleg",
  "Q12421702": "vanleg",
  "Q7425996": "vanleg",
  "Q16765345": "vanleg",
  "Q3269818": "vanleg",
  "Q2631681": "vanleg",
  "Q20427131": "vanleg",
  "Q13202368": "vanleg",
  "Q3396255": "vanleg",
  "Q1533235": "vanleg",
  "Q2723206": "vanleg",
  "Q5208800": "vanleg",
  "Q28000941": "vanleg",
  "Q705381": "vanleg",
  "Q523224": "vanleg",
  "Q596215": "vanleg",
  "Q85754826": "vanleg",
  "Q6826082": "vanleg",
  "Q17048447": "vanleg",
  "Q6967056": "vanleg",
  "Q11676485": "vanleg",
  "Q1570466": "vanleg",
  "Q10742207": "vanleg",
  "Q137609355": "vanleg",
  "Q123171413": "vanleg",
  "Q12884882": "vanleg"
}