{
    "Q1776843":  "segngjeten",
    "Q1111861":  "segngjeten",
    "Q1027725":  "sjeldgjevt",
    "Q600108":  "sjeldgjevt",
    "Q663150":  "vanleg",
    "Q843585":  "vanleg",
    "Q388952":  "vanleg",
    "Q1935178":  "vanleg",
    "Q613922":  "gudebore",
    "Q636775":  "sjeldgjevt",
    "Q1708738":  "vanleg",
    "Q516612":  "sjeldgjevt",
    "Q890298":  "vanleg",
    "Q40728":  "vanleg",
    "Q210826":  "sjeldgjevt",
    "Q1232528":  "vanleg",
    "Q786828":  "vanleg",
    "Q466602":  "vanleg",
    "Q609630":  "vanleg",
    "Q516970":  "gudebore",
    "Q692939":  "vanleg",
    "Q946221":  "sjeldgjevt",
    "Q638976":  "sjeldgjevt",
    "Q1179217":  "vanleg",
    "Q184138":  "vanleg",
    "Q1149746":  "vanleg",
    "Q620656":  "vanleg",
    "Q971182":  "vanleg",
    "Q656152":  "sjeldgjevt",
    "Q1469817":  "vanleg",
    "Q846312":  "vanleg",
    "Q1665430":  "vanleg",
    "Q571149":  "vanleg",
    "Q545962":  "vanleg",
    "Q206557":  "sjeldgjevt",
    "Q18562203":  "gudebore",
    "Q850232":  "vanleg",
    "Q1509851":  "vanleg",
    "Q288482":  "vanleg",
    "Q262924":  "vanleg",
    "Q4412725":  "vanleg",
    "Q1031529":  "segngjeten",
    "Q733396":  "vanleg",
    "Q654338":  "sjeldgjevt",
    "Q251505":  "vanleg",
    "Q489798":  "vanleg",
    "Q214720":  "vanleg",
    "Q284617":  "sjeldgjevt",
    "Q2748830":  "vanleg",
    "Q809802":  "vanleg",
    "Q848812":  "vanleg",
    "Q180552":  "vanleg",
    "Q211848":  "vanleg",
    "Q541046":  "sjeldgjevt",
    "Q673441":  "vanleg",
    "Q901301":  "vanleg",
    "Q1759668":  "sjeldgjevt",
    "Q844058":  "vanleg",
    "Q548300":  "vanleg",
    "Q217671":  "vanleg",
    "Q1593072":  "segngjeten",
    "Q749070":  "sjeldgjevt",
    "Q3044064":  "vanleg",
    "Q166777":  "vanleg",
    "Q1096752":  "vanleg",
    "Q304702":  "vanleg",
    "Q55465308":  "vanleg",
    "Q1953691":  "sjeldgjevt",
    "Q466701":  "sjeldgjevt",
    "Q523878":  "segngjeten",
    "Q857040":  "vanleg",
    "Q447136":  "vanleg",
    "Q11880004":  "vanleg",
    "Q1501738":  "sjeldgjevt",
    "Q1617933":  "sjeldgjevt",
    "Q472753":  "sjeldgjevt"
}
